typed_signals/__init__.py
typed_signals-0.1.2.dist-info/METADATA
typed_signals-0.1.2.dist-info/WHEEL
typed_signals-0.1.2.dist-info/licenses/LICENSE
typed_signals-0.1.2.dist-info/RECORD
