Metadata-Version: 2.4
Name: typed-signals
Version: 0.1.2
Summary: Lightweight, strongly-typed event and signal library for Python.
Project-URL: homepage, https://github.com/eyueldk/typed-signals
Project-URL: repository, https://github.com/eyueldk/typed-signals
Author: eyueldk
License: MIT
License-File: LICENSE
Keywords: async,events,python,signals,typed
Classifier: License :: OSI Approved :: MIT License
Classifier: Operating System :: OS Independent
Classifier: Programming Language :: Python :: 3
Classifier: Programming Language :: Python :: 3.9
Requires-Python: >=3.9
